{"PageNumber":71,"Angle":0,"RotatedAngle":0,"Height":2526,"Width":1786,"OriginHeight":0,"OriginWidth":0,"Elements":[{"Index":0,"Type":"Discard_type","Text":"H6: Compreensão de Manuais e Instruções","Level":0,"Polygon":{"LeftBottom":{"X":506,"Y":152},"LeftTop":{"X":506,"Y":107},"RightBottom":{"X":1283,"Y":152},"RightTop":{"X":1283,"Y":107}},"InsetImageName":"","Elements":null,"ImagePath":"","group_id":-1,"group_type":""},{"Index":1,"Type":"header","Text":"Professor Professor Redão","Level":0,"Polygon":{"LeftBottom":{"X":1451,"Y":220},"LeftTop":{"X":1451,"Y":109},"RightBottom":{"X":1685,"Y":220},"RightTop":{"X":1685,"Y":109}},"InsetImageName":"","Elements":null,"ImagePath":"","group_id":-1,"group_type":""},{"Index":2,"Type":"title","Text":"#  Questão 107 (H6 | 2017 | 620,2) ①②③④⑤","Level":0,"Polygon":{"LeftBottom":{"X":104,"Y":273},"LeftTop":{"X":104,"Y":230},"RightBottom":{"X":783,"Y":273},"RightTop":{"X":783,"Y":230}},"InsetImageName":"","Elements":null,"ImagePath":"","group_id":-1,"group_type":""},{"Index":3,"Type":"paragraph","Text":"No manual fornecido pelo fabricante de uma ducha elétrica de 220 V é apresentado um gráfico com a variação da temperatura da água em função da vazão para três condições (morno, quente e superquente). Na condição superquente, a potência dissipada é de 6 500 W. Considere o calor específico da água igual a 4 200 J/(kg °C) e densidade da água igual a 1 kg/L.","Level":0,"Polygon":{"LeftBottom":{"X":101,"Y":632},"LeftTop":{"X":101,"Y":301},"RightBottom":{"X":842,"Y":632},"RightTop":{"X":842,"Y":301}},"InsetImageName":"","Elements":null,"ImagePath":"","group_id":-1,"group_type":""},{"Index":4,"Type":"paragraph","Text":"Elevação de temperatura × Curva vazão","Level":0,"Polygon":{"LeftBottom":{"X":201,"Y":698},"LeftTop":{"X":201,"Y":662},"RightBottom":{"X":765,"Y":698},"RightTop":{"X":765,"Y":662}},"InsetImageName":"","Elements":null,"ImagePath":"","group_id":-1,"group_type":""},{"Index":5,"Type":"paragraph","Text":"1 - MORNO","Level":0,"Polygon":{"LeftBottom":{"X":636,"Y":736},"LeftTop":{"X":636,"Y":710},"RightBottom":{"X":774,"Y":736},"RightTop":{"X":774,"Y":710}},"InsetImageName":"","Elements":null,"ImagePath":"","group_id":-1,"group_type":""},{"Index":6,"Type":"paragraph","Text":"2-QUENTE","Level":0,"Polygon":{"LeftBottom":{"X":636,"Y":763},"LeftTop":{"X":636,"Y":738},"RightBottom":{"X":777,"Y":763},"RightTop":{"X":777,"Y":738}},"InsetImageName":"","Elements":null,"ImagePath":"","group_id":-1,"group_type":""},{"Index":7,"Type":"paragraph","Text":"3 - SUPERQUENTE","Level":0,"Polygon":{"LeftBottom":{"X":636,"Y":794},"LeftTop":{"X":636,"Y":768},"RightBottom":{"X":860,"Y":794},"RightTop":{"X":860,"Y":768}},"InsetImageName":"","Elements":null,"ImagePath":"","group_id":-1,"group_type":""},{"Index":8,"Type":"figure","Text":"","Level":0,"Polygon":{"LeftBottom":{"X":124,"Y":1087},"LeftTop":{"X":124,"Y":811},"RightBottom":{"X":861,"Y":1087},"RightTop":{"X":861,"Y":811}},"InsetImageName":"","Elements":[{"Index":0,"Type":"figure_text","Text":"|Vazão| (L/min)| |----|----| |1|3| |2|2| |3|1| |4|12| |5|8| |6|8| |7|8| |8|7| |9|8| |10|7|","Level":0,"Polygon":{"LeftBottom":{"X":124,"Y":1087},"LeftTop":{"X":124,"Y":811},"RightBottom":{"X":861,"Y":1087},"RightTop":{"X":861,"Y":811}},"InsetImageName":"","Elements":null,"ImagePath":"","group_id":0,"group_type":""}],"ImagePath":"images/085219f9ddd31fdee3979b63495cf54b-image.png","group_id":-1,"group_type":""},{"Index":9,"Type":"paragraph","Text":"Com base nas informações dadas, a potência na condição morno corresponde a que fração da potência na condição superquente?","Level":0,"Polygon":{"LeftBottom":{"X":101,"Y":1243},"LeftTop":{"X":101,"Y":1120},"RightBottom":{"X":843,"Y":1243},"RightTop":{"X":843,"Y":1120}},"InsetImageName":"","Elements":null,"ImagePath":"","group_id":-1,"group_type":""},{"Index":10,"Type":"paragraph","Text":"A $\\frac{1}{3}$","Level":0,"Polygon":{"LeftBottom":{"X":101,"Y":1357},"LeftTop":{"X":101,"Y":1281},"RightBottom":{"X":197,"Y":1357},"RightTop":{"X":197,"Y":1281}},"InsetImageName":"","Elements":null,"ImagePath":"","group_id":-1,"group_type":""},{"Index":11,"Type":"paragraph","Text":"B $\\frac{1}{5}$","Level":0,"Polygon":{"LeftBottom":{"X":102,"Y":1471},"LeftTop":{"X":102,"Y":1395},"RightBottom":{"X":195,"Y":1471},"RightTop":{"X":195,"Y":1395}},"InsetImageName":"","Elements":null,"ImagePath":"","group_id":-1,"group_type":""},{"Index":12,"Type":"paragraph","Text":"© $\\frac{3}{5}$","Level":0,"Polygon":{"LeftBottom":{"X":101,"Y":1597},"LeftTop":{"X":101,"Y":1516},"RightBottom":{"X":195,"Y":1597},"RightTop":{"X":195,"Y":1516}},"InsetImageName":"","Elements":null,"ImagePath":"","group_id":-1,"group_type":""},{"Index":13,"Type":"paragraph","Text":"D $\\frac{3}{8}$","Level":0,"Polygon":{"LeftBottom":{"X":101,"Y":1711},"LeftTop":{"X":101,"Y":1632},"RightBottom":{"X":195,"Y":1711},"RightTop":{"X":195,"Y":1632}},"InsetImageName":"","Elements":null,"ImagePath":"","group_id":-1,"group_type":""},{"Index":14,"Type":"paragraph","Text":"E $\\frac{5}{8}$","Level":0,"Polygon":{"LeftBottom":{"X":101,"Y":1827},"LeftTop":{"X":101,"Y":1748},"RightBottom":{"X":195,"Y":1827},"RightTop":{"X":195,"Y":1748}},"InsetImageName":"","Elements":null,"ImagePath":"","group_id":-1,"group_type":""},{"Index":15,"Type":"title","Text":"#  Questão 108 (H6 | 2021 | 640,7) ①②③④⑤","Level":0,"Polygon":{"LeftBottom":{"X":945,"Y":271},"LeftTop":{"X":945,"Y":230},"RightBottom":{"X":1617,"Y":271},"RightTop":{"X":1617,"Y":230}},"InsetImageName":"","Elements":null,"ImagePath":"","group_id":-1,"group_type":""},{"Index":16,"Type":"paragraph","Text":"O alcoolômetro Gay Lussac é um instrumento destinado a medir o teor de álcool, em porcentagem de volume (v/v), de soluções de água e álcool na faixa de 0 °GL a 100 °GL, com divisões de 0,1 °GL. A concepção do alcoolômetro se baseia no princípio de flutuabilidade de Arquimedes, semelhante ao funcionamento de um densímetro. A escala do instrumento é aferida a 20 °C, sendo necessária a correção da medida, caso a temperatura da solução não esteja na temperatura de aferição. É apresentada parte da tabela de correção de um alcoolômetro, com a temperatura","Level":0,"Polygon":{"LeftBottom":{"X":940,"Y":796},"LeftTop":{"X":940,"Y":301},"RightBottom":{"X":1686,"Y":796},"RightTop":{"X":1686,"Y":301}},"InsetImageName":"","Elements":null,"ImagePath":"","group_id":-1,"group_type":""},{"Index":17,"Type":"table","Text":"<table><tr><td colspan=\"7\">Tabela de correção do alcoolômetro com temperatura 20 °C</td></tr><tr><td rowspan=\"2\">°GL</td><td colspan=\"6\">Leitura da temperatura (°C)</td></tr><tr><td>20</td><td>21</td><td>22</td><td>23</td><td>24</td><td>25</td></tr><tr><td>35</td><td>35,0</td><td>34,6</td><td>34,2</td><td>33,8</td><td>33,4</td><td>33,0</td></tr><tr><td>36</td><td>36,0</td><td>35,6</td><td>35,2</td><td>34,8</td><td>34,4</td><td>34,0</td></tr></table>","Level":0,"Polygon":{"LeftBottom":{"X":940,"Y":1117},"LeftTop":{"X":940,"Y":816},"RightBottom":{"X":1683,"Y":1117},"RightTop":{"X":1683,"Y":816}},"InsetImageName":"","Elements":null,"ImagePath":"","group_id":-1,"group_type":""},{"Index":18,"Type":"paragraph","Text":"Manual alcoolômetro Gay Lussac. Disponível em: www.incoterm.com.br. Acesso em: 4 dez. 2018 (adaptado).","Level":0,"Polygon":{"LeftBottom":{"X":1045,"Y":1203},"LeftTop":{"X":1045,"Y":1140},"RightBottom":{"X":1686,"Y":1203},"RightTop":{"X":1686,"Y":1140}},"InsetImageName":"","Elements":null,"ImagePath":"","group_id":-1,"group_type":""},{"Index":19,"Type":"paragraph","Text":"É necessária a correção da medida do instrumento, pois um aumento na temperatura promove o(a)","Level":0,"Polygon":{"LeftBottom":{"X":940,"Y":1309},"LeftTop":{"X":940,"Y":1226},"RightBottom":{"X":1681,"Y":1309},"RightTop":{"X":1681,"Y":1226}},"InsetImageName":"","Elements":null,"ImagePath":"","group_id":-1,"group_type":""},{"Index":20,"Type":"paragraph","Text":"A aumento da dissociação da água.","Level":0,"Polygon":{"LeftBottom":{"X":945,"Y":1377},"LeftTop":{"X":945,"Y":1334},"RightBottom":{"X":1481,"Y":1377},"RightTop":{"X":1481,"Y":1334}},"InsetImageName":"","Elements":null,"ImagePath":"","group_id":-1,"group_type":""},{"Index":21,"Type":"paragraph","Text":"B aumento da densidade da água e do álcool.","Level":0,"Polygon":{"LeftBottom":{"X":945,"Y":1443},"LeftTop":{"X":945,"Y":1402},"RightBottom":{"X":1631,"Y":1443},"RightTop":{"X":1631,"Y":1402}},"InsetImageName":"","Elements":null,"ImagePath":"","group_id":-1,"group_type":""},{"Index":22,"Type":"paragraph","Text":"© mudança do volume dos materiais por dilatação.","Level":0,"Polygon":{"LeftBottom":{"X":945,"Y":1514},"LeftTop":{"X":945,"Y":1471},"RightBottom":{"X":1695,"Y":1514},"RightTop":{"X":1695,"Y":1471}},"InsetImageName":"","Elements":null,"ImagePath":"","group_id":-1,"group_type":""},{"Index":23,"Type":"paragraph","Text":"Ⓓ aumento da concentração de alcool durante a medida.","Level":0,"Polygon":{"LeftBottom":{"X":945,"Y":1622},"LeftTop":{"X":945,"Y":1539},"RightBottom":{"X":1697,"Y":1622},"RightTop":{"X":1697,"Y":1539}},"InsetImageName":"","Elements":null,"ImagePath":"","group_id":-1,"group_type":""},{"Index":24,"Type":"paragraph","Text":"E alteração das propriedades químicas da mistura alcool e água.","Level":0,"Polygon":{"LeftBottom":{"X":945,"Y":1731},"LeftTop":{"X":945,"Y":1650},"RightBottom":{"X":1697,"Y":1731},"RightTop":{"X":1697,"Y":1650}},"InsetImageName":"","Elements":null,"ImagePath":"","group_id":-1,"group_type":""},{"Index":25,"Type":"footer","Text":"Competência 2 | Natureza por Habilidades e Dificuldades dos Itens","Level":0,"Polygon":{"LeftBottom":{"X":485,"Y":2479},"LeftTop":{"X":485,"Y":2441},"RightBottom":{"X":1317,"Y":2479},"RightTop":{"X":1317,"Y":2441}},"InsetImageName":"","Elements":null,"ImagePath":"","group_id":-1,"group_type":""},{"Index":26,"Type":"footer","Text":"Página 77","Level":0,"Polygon":{"LeftBottom":{"X":1706,"Y":2388},"LeftTop":{"X":1706,"Y":2226},"RightBottom":{"X":1763,"Y":2388},"RightTop":{"X":1763,"Y":2226}},"InsetImageName":"","Elements":null,"ImagePath":"","group_id":-1,"group_type":""}]}