{"PageNumber":54,"Angle":0,"RotatedAngle":0,"Height":2526,"Width":1786,"OriginHeight":0,"OriginWidth":0,"Elements":[{"Index":0,"Type":"header","Text":"H4: Sustentabilidade e Conservação Ambiental","Level":0,"Polygon":{"LeftBottom":{"X":472,"Y":152},"LeftTop":{"X":472,"Y":104},"RightBottom":{"X":1315,"Y":152},"RightTop":{"X":1315,"Y":104}},"InsetImageName":"","Elements":null,"ImagePath":"","group_id":-1,"group_type":""},{"Index":1,"Type":"header","Text":"Professor Fredão","Level":0,"Polygon":{"LeftBottom":{"X":1453,"Y":220},"LeftTop":{"X":1453,"Y":107},"RightBottom":{"X":1686,"Y":220},"RightTop":{"X":1686,"Y":107}},"InsetImageName":"","Elements":null,"ImagePath":"","group_id":-1,"group_type":""},{"Index":2,"Type":"title","Text":"#  Questão 074 (H4 | 2022 | 585,5) ①②③④⑤","Level":0,"Polygon":{"LeftBottom":{"X":99,"Y":273},"LeftTop":{"X":99,"Y":228},"RightBottom":{"X":777,"Y":273},"RightTop":{"X":777,"Y":228}},"InsetImageName":"","Elements":null,"ImagePath":"","group_id":-1,"group_type":""},{"Index":3,"Type":"paragraph","Text":"Os resultados de um ensaio clínico randomizado na Indonésia apontaram uma redução de 77% dos casos de dengue nas áreas que receberam o mosquito Aedes aegypti infectado com a bactéria Wolbachia. Trata-se da mesma técnica utilizada no Brasil pelo Método Wolbachia, iniciativa conduzida pela Fundação Oswaldo Cruz — Fiocruz. Essa bactéria induz a redução da carga viral no mosquito e, consequentemente, o número de casos de dengue na área, sendo repassada por meio do cruzamento entre os insetos. Como essa bactéria é um organismo intracelular e o vírus também precisa entrar nas células para se reproduzir, ambos necessitarão de recursos comuns.","Level":0,"Polygon":{"LeftBottom":{"X":95,"Y":804},"LeftTop":{"X":95,"Y":294},"RightBottom":{"X":849,"Y":804},"RightTop":{"X":849,"Y":294}},"InsetImageName":"","Elements":null,"ImagePath":"","group_id":-1,"group_type":""},{"Index":4,"Type":"paragraph","Text":"COSTA, G. Agência Fiocruz de Notícias. Estudo confirma eficácia do Método Wolbachia para dengue. Disponível em: https://portal.fiocruz.br. Acesso em: 3 jun. 2022 (adaptado).","Level":0,"Polygon":{"LeftBottom":{"X":104,"Y":912},"LeftTop":{"X":104,"Y":819},"RightBottom":{"X":847,"Y":912},"RightTop":{"X":847,"Y":819}},"InsetImageName":"","Elements":null,"ImagePath":"","group_id":-1,"group_type":""},{"Index":5,"Type":"paragraph","Text":"Essa tecnologia utilizada no combate à dengue consiste na","Level":0,"Polygon":{"LeftBottom":{"X":95,"Y":1003},"LeftTop":{"X":95,"Y":930},"RightBottom":{"X":847,"Y":1003},"RightTop":{"X":847,"Y":930}},"InsetImageName":"","Elements":null,"ImagePath":"","group_id":-1,"group_type":""},{"Index":6,"Type":"paragraph","Text":"A predação do vírus pela bactéria.","Level":0,"Polygon":{"LeftBottom":{"X":99,"Y":1072},"LeftTop":{"X":99,"Y":1029},"RightBottom":{"X":624,"Y":1072},"RightTop":{"X":624,"Y":1029}},"InsetImageName":"","Elements":null,"ImagePath":"","group_id":-1,"group_type":""},{"Index":7,"Type":"paragraph","Text":"B esterilização de mosquitos infectados.","Level":0,"Polygon":{"LeftBottom":{"X":99,"Y":1135},"LeftTop":{"X":99,"Y":1089},"RightBottom":{"X":704,"Y":1135},"RightTop":{"X":704,"Y":1089}},"InsetImageName":"","Elements":null,"ImagePath":"","group_id":-1,"group_type":""},{"Index":8,"Type":"paragraph","Text":"C alteração no genótipo do mosquito pela bactéria.","Level":0,"Polygon":{"LeftBottom":{"X":99,"Y":1198},"LeftTop":{"X":99,"Y":1152},"RightBottom":{"X":852,"Y":1198},"RightTop":{"X":852,"Y":1152}},"InsetImageName":"","Elements":null,"ImagePath":"","group_id":-1,"group_type":""},{"Index":9,"Type":"paragraph","Text":"Ⓓ competição do vírus e da bactéria no hospedeiro.","Level":0,"Polygon":{"LeftBottom":{"X":99,"Y":1263},"LeftTop":{"X":99,"Y":1218},"RightBottom":{"X":858,"Y":1263},"RightTop":{"X":858,"Y":1218}},"InsetImageName":"","Elements":null,"ImagePath":"","group_id":-1,"group_type":""},{"Index":10,"Type":"paragraph","Text":"E inserção de material genético do vírus na bactéria.","Level":0,"Polygon":{"LeftBottom":{"X":99,"Y":1354},"LeftTop":{"X":99,"Y":1281},"RightBottom":{"X":858,"Y":1354},"RightTop":{"X":858,"Y":1281}},"InsetImageName":"","Elements":null,"ImagePath":"","group_id":-1,"group_type":""},{"Index":11,"Type":"title","Text":"#  Questão 075 (H4 | 2018 | 601,6) ①②③④⑤","Level":0,"Polygon":{"LeftBottom":{"X":95,"Y":1481},"LeftTop":{"X":95,"Y":1433},"RightBottom":{"X":783,"Y":1481},"RightTop":{"X":783,"Y":1433}},"InsetImageName":"","Elements":null,"ImagePath":"","group_id":-1,"group_type":""},{"Index":12,"Type":"paragraph","Text":"Corredores ecológicos visam mitigar os efeitos da fragmentação dos ecossistemas promovendo a ligação entre diferentes áreas, com o objetivo de proporcionar o deslocamento de animais, a dispersão de sementes e o aumento da cobertura vegetal. São instituídos com base em informações como estudos sobre o deslocamento de espécies, sua área de vida (área necessária para o suprimento de suas necessidades vitais e reprodutivas) e a distribuição de suas populações.","Level":0,"Polygon":{"LeftBottom":{"X":95,"Y":1867},"LeftTop":{"X":95,"Y":1498},"RightBottom":{"X":847,"Y":1867},"RightTop":{"X":847,"Y":1498}},"InsetImageName":"","Elements":null,"ImagePath":"","group_id":-1,"group_type":""},{"Index":13,"Type":"paragraph","Text":"Disponível em: www.mma.gov.br. Acesso em: 30 nov. 2017\n(adaptado).","Level":0,"Polygon":{"LeftBottom":{"X":195,"Y":1946},"LeftTop":{"X":195,"Y":1880},"RightBottom":{"X":845,"Y":1946},"RightTop":{"X":845,"Y":1880}},"InsetImageName":"","Elements":null,"ImagePath":"","group_id":-1,"group_type":""},{"Index":14,"Type":"paragraph","Text":"Nessa estratégia, a recuperação da biodiversidade é efetiva porque","Level":0,"Polygon":{"LeftBottom":{"X":95,"Y":2039},"LeftTop":{"X":95,"Y":1961},"RightBottom":{"X":847,"Y":2039},"RightTop":{"X":847,"Y":1961}},"InsetImageName":"","Elements":null,"ImagePath":"","group_id":-1,"group_type":""},{"Index":15,"Type":"paragraph","Text":"A propicia o fluxo gênico.","Level":0,"Polygon":{"LeftBottom":{"X":99,"Y":2105},"LeftTop":{"X":99,"Y":2059},"RightBottom":{"X":495,"Y":2105},"RightTop":{"X":495,"Y":2059}},"InsetImageName":"","Elements":null,"ImagePath":"","group_id":-1,"group_type":""},{"Index":16,"Type":"paragraph","Text":"B intensifica o manejo de espécies.","Level":0,"Polygon":{"LeftBottom":{"X":99,"Y":2168},"LeftTop":{"X":99,"Y":2122},"RightBottom":{"X":640,"Y":2168},"RightTop":{"X":640,"Y":2122}},"InsetImageName":"","Elements":null,"ImagePath":"","group_id":-1,"group_type":""},{"Index":17,"Type":"paragraph","Text":"© amplia o processo de ocupação humana.","Level":0,"Polygon":{"LeftBottom":{"X":99,"Y":2231},"LeftTop":{"X":99,"Y":2185},"RightBottom":{"X":751,"Y":2231},"RightTop":{"X":751,"Y":2185}},"InsetImageName":"","Elements":null,"ImagePath":"","group_id":-1,"group_type":""},{"Index":18,"Type":"paragraph","Text":"D aumenta o número de indivíduos nas populações.","Level":0,"Polygon":{"LeftBottom":{"X":99,"Y":2297},"LeftTop":{"X":99,"Y":2251},"RightBottom":{"X":858,"Y":2297},"RightTop":{"X":858,"Y":2251}},"InsetImageName":"","Elements":null,"ImagePath":"","group_id":-1,"group_type":""},{"Index":19,"Type":"paragraph","Text":"E favorece a formação de ilhas de proteção integral.","Level":0,"Polygon":{"LeftBottom":{"X":99,"Y":2362},"LeftTop":{"X":99,"Y":2317},"RightBottom":{"X":858,"Y":2362},"RightTop":{"X":858,"Y":2317}},"InsetImageName":"","Elements":null,"ImagePath":"","group_id":-1,"group_type":""},{"Index":20,"Type":"title","Text":"##  Questão 076 (H4 | 2020 | 612,4) ①②③④⑤","Level":0,"Polygon":{"LeftBottom":{"X":936,"Y":273},"LeftTop":{"X":936,"Y":228},"RightBottom":{"X":1619,"Y":273},"RightTop":{"X":1619,"Y":228}},"InsetImageName":"","Elements":null,"ImagePath":"","group_id":-1,"group_type":""},{"Index":21,"Type":"paragraph","Text":"A fragmentação dos hábitats é caracterizada pela formação de ilhas da paisagem original, circundadas por áreas transformadas. Esse tipo de interferência no ambiente ameaça a biodiversidade. Imagine que uma população de onças foi isolada em uma mata pequena. Elas se extinguiriam mesmo sem terem sido abatidas. Diversos componentes da ilha de hábitat, como o tamanho, a heterogeneidade, o seu entorno, a sua conectividade e o efeito de borda são determinantes para a persistência ou não das espécies originais.","Level":0,"Polygon":{"LeftBottom":{"X":933,"Y":698},"LeftTop":{"X":933,"Y":294},"RightBottom":{"X":1686,"Y":698},"RightTop":{"X":1686,"Y":294}},"InsetImageName":"","Elements":null,"ImagePath":"","group_id":-1,"group_type":""},{"Index":22,"Type":"paragraph","Text":"Uma medida que auxilia na conservação da biodiversidade nas ilhas mencionadas no texto compreende a","Level":0,"Polygon":{"LeftBottom":{"X":936,"Y":829},"LeftTop":{"X":936,"Y":715},"RightBottom":{"X":1686,"Y":829},"RightTop":{"X":1686,"Y":715}},"InsetImageName":"","Elements":null,"ImagePath":"","group_id":-1,"group_type":""},{"Index":23,"Type":"paragraph","Text":"A formação de micro-hábitats.","Level":0,"Polygon":{"LeftBottom":{"X":942,"Y":895},"LeftTop":{"X":942,"Y":852},"RightBottom":{"X":1403,"Y":895},"RightTop":{"X":1403,"Y":852}},"InsetImageName":"","Elements":null,"ImagePath":"","group_id":-1,"group_type":""},{"Index":24,"Type":"paragraph","Text":"B ampliação do efeito de borda.","Level":0,"Polygon":{"LeftBottom":{"X":942,"Y":958},"LeftTop":{"X":942,"Y":915},"RightBottom":{"X":1429,"Y":958},"RightTop":{"X":1429,"Y":915}},"InsetImageName":"","Elements":null,"ImagePath":"","group_id":-1,"group_type":""},{"Index":25,"Type":"paragraph","Text":"C construção de corredores ecológicos.","Level":0,"Polygon":{"LeftBottom":{"X":942,"Y":1018},"LeftTop":{"X":942,"Y":976},"RightBottom":{"X":1536,"Y":1018},"RightTop":{"X":1536,"Y":976}},"InsetImageName":"","Elements":null,"ImagePath":"","group_id":-1,"group_type":""},{"Index":26,"Type":"paragraph","Text":"D promoção da sucessão ecológica.","Level":0,"Polygon":{"LeftBottom":{"X":942,"Y":1082},"LeftTop":{"X":942,"Y":1039},"RightBottom":{"X":1488,"Y":1082},"RightTop":{"X":1488,"Y":1039}},"InsetImageName":"","Elements":null,"ImagePath":"","group_id":-1,"group_type":""},{"Index":27,"Type":"paragraph","Text":"E introdução de novas espécies de animais e vegetais.","Level":0,"Polygon":{"LeftBottom":{"X":942,"Y":1183},"LeftTop":{"X":942,"Y":1102},"RightBottom":{"X":1701,"Y":1183},"RightTop":{"X":1701,"Y":1102}},"InsetImageName":"","Elements":null,"ImagePath":"","group_id":-1,"group_type":""},{"Index":28,"Type":"title","Text":"#  Questão 077 (H4 | 2013 | 615,4) ①②③④⑤","Level":0,"Polygon":{"LeftBottom":{"X":936,"Y":1299},"LeftTop":{"X":936,"Y":1253},"RightBottom":{"X":1619,"Y":1299},"RightTop":{"X":1619,"Y":1253}},"InsetImageName":"","Elements":null,"ImagePath":"","group_id":-1,"group_type":""},{"Index":29,"Type":"paragraph","Text":"Entre as substâncias usadas para o tratamento de água está o sulfato de alumínio que, em meio alcalino, forma partículas em suspensão na água, às quais as impurezas presentes no meio se aderem.","Level":0,"Polygon":{"LeftBottom":{"X":933,"Y":1468},"LeftTop":{"X":933,"Y":1319},"RightBottom":{"X":1686,"Y":1468},"RightTop":{"X":1686,"Y":1319}},"InsetImageName":"","Elements":null,"ImagePath":"","group_id":-1,"group_type":""},{"Index":30,"Type":"paragraph","Text":"O método de separação comumente usado para retirar o sulfato de alumínio com as impurezas aderidas é a","Level":0,"Polygon":{"LeftBottom":{"X":936,"Y":1599},"LeftTop":{"X":936,"Y":1486},"RightBottom":{"X":1686,"Y":1599},"RightTop":{"X":1686,"Y":1486}},"InsetImageName":"","Elements":null,"ImagePath":"","group_id":-1,"group_type":""},{"Index":31,"Type":"paragraph","Text":"A flotação.","Level":0,"Polygon":{"LeftBottom":{"X":942,"Y":1663},"LeftTop":{"X":942,"Y":1622},"RightBottom":{"X":1135,"Y":1663},"RightTop":{"X":1135,"Y":1622}},"InsetImageName":"","Elements":null,"ImagePath":"","group_id":-1,"group_type":""},{"Index":32,"Type":"paragraph","Text":"B levigação.","Level":0,"Polygon":{"LeftBottom":{"X":942,"Y":1728},"LeftTop":{"X":942,"Y":1685},"RightBottom":{"X":1156,"Y":1728},"RightTop":{"X":1156,"Y":1685}},"InsetImageName":"","Elements":null,"ImagePath":"","group_id":-1,"group_type":""},{"Index":33,"Type":"paragraph","Text":"C ventilação.","Level":0,"Polygon":{"LeftBottom":{"X":942,"Y":1791},"LeftTop":{"X":942,"Y":1748},"RightBottom":{"X":1163,"Y":1791},"RightTop":{"X":1163,"Y":1748}},"InsetImageName":"","Elements":null,"ImagePath":"","group_id":-1,"group_type":""},{"Index":34,"Type":"paragraph","Text":"D peneiração.","Level":0,"Polygon":{"LeftBottom":{"X":942,"Y":1855},"LeftTop":{"X":942,"Y":1812},"RightBottom":{"X":1179,"Y":1855},"RightTop":{"X":1179,"Y":1812}},"InsetImageName":"","Elements":null,"ImagePath":"","group_id":-1,"group_type":""},{"Index":35,"Type":"paragraph","Text":"E centrifugação.","Level":0,"Polygon":{"LeftBottom":{"X":942,"Y":1918},"LeftTop":{"X":942,"Y":1875},"RightBottom":{"X":1211,"Y":1918},"RightTop":{"X":1211,"Y":1875}},"InsetImageName":"","Elements":null,"ImagePath":"","group_id":-1,"group_type":""},{"Index":36,"Type":"footer","Text":"Página 60","Level":0,"Polygon":{"LeftBottom":{"X":1704,"Y":2393},"LeftTop":{"X":1704,"Y":2226},"RightBottom":{"X":1765,"Y":2393},"RightTop":{"X":1765,"Y":2226}},"InsetImageName":"","Elements":null,"ImagePath":"","group_id":-1,"group_type":""},{"Index":37,"Type":"footer","Text":"Competência 1 | Natureza por Habilidades e Dificuldades dos Itens","Level":0,"Polygon":{"LeftBottom":{"X":485,"Y":2481},"LeftTop":{"X":485,"Y":2441},"RightBottom":{"X":1315,"Y":2481},"RightTop":{"X":1315,"Y":2441}},"InsetImageName":"","Elements":null,"ImagePath":"","group_id":-1,"group_type":""}]}